{
	"response": {
		"header": {
			"resultCode": "00",
			"resultMsg": "NORMAL SERVICE."
		},
		"body": {
			"items": {
				"item": [
					{
						"거래금액": "10,400",
						"건축년도": "2001",
						"년": "2019",
						"도로명": "삼백로",
						"도로명건물본번호코드": "00257",
						"도로명건물부번호코드": "00000",
						"도로명시군구코드": "47250",
						"도로명일련번호코드": "02",
						"도로명지상지하코드": "0",
						"도로명코드": "3311028",
						"법정동": "복룡동",
						"법정동본번코드": "0245",
						"법정동부번코드": "0000",
						"법정동시군구코드": "47250",
						"법정동읍면동코드": "10400",
						"법정동지번코드": "1",
						"아파트": "주공6",
						"월": "12",
						"일": "4",
						"일련번호": "47250-39",
						"전용면적": "49.81",
						"지번": "245",
						"지역코드": "47250",
						"층": "5"
					},
					{
						"거래금액": "21,800",
						"건축년도": "1995",
						"년": "2019",
						"도로명": "복룡3길",
						"도로명건물본번호코드": "00007",
						"도로명건물부번호코드": "00000",
						"도로명시군구코드": "47250",
						"도로명일련번호코드": "01",
						"도로명지상지하코드": "0",
						"도로명코드": "4733317",
						"법정동": "복룡동",
						"법정동본번코드": "0230",
						"법정동부번코드": "0011",
						"법정동시군구코드": "47250",
						"법정동읍면동코드": "10400",
						"법정동지번코드": "1",
						"아파트": "우방1",
						"월": "12",
						"일": "21",
						"일련번호": "47250-7",
						"전용면적": "134.805",
						"지번": "230-11",
						"지역코드": "47250",
						"층": "11"
					},
					{
						"거래금액": "13,200",
						"건축년도": "2001",
						"년": "2019",
						"도로명": "삼백로",
						"도로명건물본번호코드": "00257",
						"도로명건물부번호코드": "00000",
						"도로명시군구코드": "47250",
						"도로명일련번호코드": "02",
						"도로명지상지하코드": "0",
						"도로명코드": "3311028",
						"법정동": "복룡동",
						"법정동본번코드": "0245",
						"법정동부번코드": "0000",
						"법정동시군구코드": "47250",
						"법정동읍면동코드": "10400",
						"법정동지번코드": "1",
						"아파트": "주공6",
						"월": "12",
						"일": "28",
						"일련번호": "47250-39",
						"전용면적": "59.89",
						"지번": "245",
						"지역코드": "47250",
						"층": "2"
					},
					{
						"거래금액": "5,600",
						"건축년도": "1999",
						"년": "2019",
						"도로명": "복룡냉림길",
						"도로명건물본번호코드": "00037",
						"도로명건물부번호코드": "00000",
						"도로명시군구코드": "47250",
						"도로명일련번호코드": "02",
						"도로명지상지하코드": "0",
						"도로명코드": "4733319",
						"법정동": "냉림동",
						"법정동본번코드": "0042",
						"법정동부번코드": "0001",
						"법정동시군구코드": "47250",
						"법정동읍면동코드": "10500",
						"법정동지번코드": "1",
						"아파트": "부민강변타운",
						"월": "12",
						"일": "4",
						"일련번호": "47250-45",
						"전용면적": "39.7602",
						"지번": "42-1",
						"지역코드": "47250",
						"층": "2"
					},
					{
						"거래금액": "20,900",
						"건축년도": "2011",
						"년": "2019",
						"도로명": "영남제일로",
						"도로명건물본번호코드": "01651",
						"도로명건물부번호코드": "00000",
						"도로명시군구코드": "47250",
						"도로명일련번호코드": "02",
						"도로명지상지하코드": "0",
						"도로명코드": "3311045",
						"법정동": "냉림동",
						"법정동본번코드": "0111",
						"법정동부번코드": "0000",
						"법정동시군구코드": "47250",
						"법정동읍면동코드": "10500",
						"법정동지번코드": "1",
						"아파트": "지엘리더스파크골드(101동102동)",
						"월": "12",
						"일": "6",
						"일련번호": "47250-217",
						"전용면적": "84.0714",
						"지번": "111",
						"지역코드": "47250",
						"층": "2"
					},
					{
						"거래금액": "7,600",
						"건축년도": "1995",
						"년": "2019",
						"도로명": "냉림2길",
						"도로명건물본번호코드": "00111",
						"도로명건물부번호코드": "00000",
						"도로명시군구코드": "47250",
						"도로명일련번호코드": "01",
						"도로명지상지하코드": "0",
						"도로명코드": "4733149",
						"법정동": "냉림동",
						"법정동본번코드": "0078",
						"법정동부번코드": "0000",
						"법정동시군구코드": "47250",
						"법정동읍면동코드": "10500",
						"법정동지번코드": "1",
						"아파트": "냉림4주공(203동204동205동)",
						"월": "12",
						"일": "7",
						"일련번호": "47250-33",
						"전용면적": "49.94",
						"지번": "78",
						"지역코드": "47250",
						"층": "14"
					},
					{
						"거래금액": "5,400",
						"건축년도": "1995",
						"년": "2019",
						"도로명": "냉림2길",
						"도로명건물본번호코드": "00111",
						"도로명건물부번호코드": "00000",
						"도로명시군구코드": "47250",
						"도로명일련번호코드": "01",
						"도로명지상지하코드": "0",
						"도로명코드": "4733149",
						"법정동": "냉림동",
						"법정동본번코드": "0078",
						"법정동부번코드": "0000",
						"법정동시군구코드": "47250",
						"법정동읍면동코드": "10500",
						"법정동지번코드": "1",
						"아파트": "냉림4주공(203동204동205동)",
						"월": "12",
						"일": "13",
						"일련번호": "47250-33",
						"전용면적": "38.64",
						"지번": "78",
						"지역코드": "47250",
						"층": "12"
					},
					{
						"거래금액": "21,700",
						"건축년도": "2011",
						"년": "2019",
						"도로명": "영남제일로",
						"도로명건물본번호코드": "01649",
						"도로명건물부번호코드": "00000",
						"도로명시군구코드": "47250",
						"도로명일련번호코드": "02",
						"도로명지상지하코드": "0",
						"도로명코드": "3311045",
						"법정동": "냉림동",
						"법정동본번코드": "0111",
						"법정동부번코드": "0005",
						"법정동시군구코드": "47250",
						"법정동읍면동코드": "10500",
						"법정동지번코드": "1",
						"아파트": "지엘리더스파크골드(201동202동)",
						"월": "12",
						"일": "13",
						"일련번호": "47250-219",
						"전용면적": "84.0714",
						"지번": "111-5",
						"지역코드": "47250",
						"층": "8"
					},
					{
						"거래금액": "5,350",
						"건축년도": "1999",
						"년": "2019",
						"도로명": "복룡냉림길",
						"도로명건물본번호코드": "00037",
						"도로명건물부번호코드": "00000",
						"도로명시군구코드": "47250",
						"도로명일련번호코드": "02",
						"도로명지상지하코드": "0",
						"도로명코드": "4733319",
						"법정동": "냉림동",
						"법정동본번코드": "0042",
						"법정동부번코드": "0001",
						"법정동시군구코드": "47250",
						"법정동읍면동코드": "10500",
						"법정동지번코드": "1",
						"아파트": "부민강변타운",
						"월": "12",
						"일": "16",
						"일련번호": "47250-45",
						"전용면적": "39.7602",
						"지번": "42-1",
						"지역코드": "47250",
						"층": "3"
					},
					{
						"거래금액": "6,300",
						"건축년도": "1995",
						"년": "2019",
						"도로명": "냉림2길",
						"도로명건물본번호코드": "00111",
						"도로명건물부번호코드": "00000",
						"도로명시군구코드": "47250",
						"도로명일련번호코드": "01",
						"도로명지상지하코드": "0",
						"도로명코드": "4733149",
						"법정동": "냉림동",
						"법정동본번코드": "0078",
						"법정동부번코드": "0000",
						"법정동시군구코드": "47250",
						"법정동읍면동코드": "10500",
						"법정동지번코드": "1",
						"아파트": "냉림4주공(203동204동205동)",
						"월": "12",
						"일": "17",
						"일련번호": "47250-33",
						"전용면적": "38.64",
						"지번": "78",
						"지역코드": "47250",
						"층": "14"
					}
				]
			},
			"numOfRows": "10",
			"pageNo": "1",
			"totalCount": "33"
		}
	}
}