{
	"response": {
		"header": {
			"resultCode": "00",
			"resultMsg": "NORMAL SERVICE."
		},
		"body": {
			"items": {
				"item": [
					{
						"거래금액": "30,500",
						"건축년도": "2003",
						"년": "2019",
						"도로명": "안산천남1로",
						"도로명건물본번호코드": "00100",
						"도로명건물부번호코드": "00000",
						"도로명시군구코드": "41271",
						"도로명일련번호코드": "01",
						"도로명지상지하코드": "0",
						"도로명코드": "3190051",
						"법정동": "이동",
						"법정동본번코드": "0664",
						"법정동부번코드": "0000",
						"법정동시군구코드": "41271",
						"법정동읍면동코드": "10200",
						"법정동지번코드": "1",
						"아파트": "주공그린빌10단지",
						"월": "12",
						"일": "20",
						"일련번호": "41271-48",
						"전용면적": "84.99",
						"지번": "664",
						"지역코드": "41271",
						"층": "14"
					},
					{
						"거래금액": "30,000",
						"건축년도": "2003",
						"년": "2019",
						"도로명": "안산천남1로",
						"도로명건물본번호코드": "00100",
						"도로명건물부번호코드": "00000",
						"도로명시군구코드": "41271",
						"도로명일련번호코드": "01",
						"도로명지상지하코드": "0",
						"도로명코드": "3190051",
						"법정동": "이동",
						"법정동본번코드": "0664",
						"법정동부번코드": "0000",
						"법정동시군구코드": "41271",
						"법정동읍면동코드": "10200",
						"법정동지번코드": "1",
						"아파트": "주공그린빌10단지",
						"월": "12",
						"일": "21",
						"일련번호": "41271-48",
						"전용면적": "84.99",
						"지번": "664",
						"지역코드": "41271",
						"층": "6"
					},
					{
						"거래금액": "58,000",
						"건축년도": "2005",
						"년": "2019",
						"도로명": "해양1로",
						"도로명건물본번호코드": "00030",
						"도로명건물부번호코드": "00000",
						"도로명시군구코드": "41271",
						"도로명일련번호코드": "01",
						"도로명지상지하코드": "0",
						"도로명코드": "3190077",
						"법정동": "사동",
						"법정동본번코드": "1510",
						"법정동부번코드": "0000",
						"법정동시군구코드": "41271",
						"법정동읍면동코드": "10300",
						"법정동지번코드": "1",
						"아파트": "안산고잔7차푸르지오",
						"월": "12",
						"일": "2",
						"일련번호": "41271-2554",
						"전용면적": "194.978",
						"지번": "1510",
						"지역코드": "41271",
						"층": "21"
					},
					{
						"거래금액": "10,500",
						"건축년도": "1994",
						"년": "2019",
						"도로명": "선진로",
						"도로명건물본번호코드": "00114",
						"도로명건물부번호코드": "00000",
						"도로명시군구코드": "41271",
						"도로명일련번호코드": "01",
						"도로명지상지하코드": "0",
						"도로명코드": "3190042",
						"법정동": "사동",
						"법정동본번코드": "1505",
						"법정동부번코드": "0000",
						"법정동시군구코드": "41271",
						"법정동읍면동코드": "10300",
						"법정동지번코드": "1",
						"아파트": "본오2",
						"월": "12",
						"일": "2",
						"일련번호": "41271-11",
						"전용면적": "46.05",
						"지번": "1505",
						"지역코드": "41271",
						"층": "3"
					},
					{
						"거래금액": "20,000",
						"건축년도": "1994",
						"년": "2019",
						"도로명": "감골2로",
						"도로명건물본번호코드": "00047",
						"도로명건물부번호코드": "00000",
						"도로명시군구코드": "41271",
						"도로명일련번호코드": "01",
						"도로명지상지하코드": "0",
						"도로명코드": "3190006",
						"법정동": "사동",
						"법정동본번코드": "1345",
						"법정동부번코드": "0001",
						"법정동시군구코드": "41271",
						"법정동읍면동코드": "10300",
						"법정동지번코드": "1",
						"아파트": "요진",
						"월": "12",
						"일": "2",
						"일련번호": "41271-16",
						"전용면적": "77.665",
						"지번": "1345-1",
						"지역코드": "41271",
						"층": "2"
					},
					{
						"거래금액": "36,000",
						"건축년도": "2005",
						"년": "2019",
						"도로명": "해양1로",
						"도로명건물본번호코드": "00011",
						"도로명건물부번호코드": "00000",
						"도로명시군구코드": "41271",
						"도로명일련번호코드": "01",
						"도로명지상지하코드": "0",
						"도로명코드": "3190077",
						"법정동": "사동",
						"법정동본번코드": "1512",
						"법정동부번코드": "0000",
						"법정동시군구코드": "41271",
						"법정동읍면동코드": "10300",
						"법정동지번코드": "1",
						"아파트": "안산고잔6차푸르지오",
						"월": "12",
						"일": "2",
						"일련번호": "41271-2570",
						"전용면적": "100.207",
						"지번": "1512",
						"지역코드": "41271",
						"층": "17"
					},
					{
						"거래금액": "18,800",
						"건축년도": "2000",
						"년": "2019",
						"도로명": "광덕4로",
						"도로명건물본번호코드": "00460",
						"도로명건물부번호코드": "00000",
						"도로명시군구코드": "41271",
						"도로명일련번호코드": "02",
						"도로명지상지하코드": "0",
						"도로명코드": "3190012",
						"법정동": "사동",
						"법정동본번코드": "1536",
						"법정동부번코드": "0000",
						"법정동시군구코드": "41271",
						"법정동읍면동코드": "10300",
						"법정동지번코드": "1",
						"아파트": "푸른마을주공5",
						"월": "12",
						"일": "2",
						"일련번호": "41271-51",
						"전용면적": "49.99",
						"지번": "1536",
						"지역코드": "41271",
						"층": "10"
					},
					{
						"거래금액": "19,500",
						"건축년도": "2000",
						"년": "2019",
						"도로명": "광덕4로",
						"도로명건물본번호코드": "00460",
						"도로명건물부번호코드": "00000",
						"도로명시군구코드": "41271",
						"도로명일련번호코드": "02",
						"도로명지상지하코드": "0",
						"도로명코드": "3190012",
						"법정동": "사동",
						"법정동본번코드": "1536",
						"법정동부번코드": "0000",
						"법정동시군구코드": "41271",
						"법정동읍면동코드": "10300",
						"법정동지번코드": "1",
						"아파트": "푸른마을주공5",
						"월": "12",
						"일": "5",
						"일련번호": "41271-51",
						"전용면적": "49.99",
						"지번": "1536",
						"지역코드": "41271",
						"층": "4"
					},
					{
						"거래금액": "29,500",
						"건축년도": "2005",
						"년": "2019",
						"도로명": "해양1로",
						"도로명건물본번호코드": "00011",
						"도로명건물부번호코드": "00000",
						"도로명시군구코드": "41271",
						"도로명일련번호코드": "01",
						"도로명지상지하코드": "0",
						"도로명코드": "3190077",
						"법정동": "사동",
						"법정동본번코드": "1512",
						"법정동부번코드": "0000",
						"법정동시군구코드": "41271",
						"법정동읍면동코드": "10300",
						"법정동지번코드": "1",
						"아파트": "안산고잔6차푸르지오",
						"월": "12",
						"일": "5",
						"일련번호": "41271-2570",
						"전용면적": "88.982",
						"지번": "1512",
						"지역코드": "41271",
						"층": "1"
					},
					{
						"거래금액": "41,000",
						"건축년도": "2005",
						"년": "2019",
						"도로명": "해양1로",
						"도로명건물본번호코드": "00011",
						"도로명건물부번호코드": "00000",
						"도로명시군구코드": "41271",
						"도로명일련번호코드": "01",
						"도로명지상지하코드": "0",
						"도로명코드": "3190077",
						"법정동": "사동",
						"법정동본번코드": "1512",
						"법정동부번코드": "0000",
						"법정동시군구코드": "41271",
						"법정동읍면동코드": "10300",
						"법정동지번코드": "1",
						"아파트": "안산고잔6차푸르지오",
						"월": "12",
						"일": "5",
						"일련번호": "41271-2570",
						"전용면적": "120.651",
						"지번": "1512",
						"지역코드": "41271",
						"층": "18"
					}
				]
			},
			"numOfRows": "10",
			"pageNo": "1",
			"totalCount": "171"
		}
	}
}