{
	"response": {
		"header": {
			"resultCode": "00",
			"resultMsg": "NORMAL SERVICE."
		},
		"body": {
			"items": {
				"item": [
					{
						"거래금액": "15,100",
						"건축년도": "2003",
						"년": "2019",
						"도로명": "충효로",
						"도로명건물본번호코드": "00075",
						"도로명건물부번호코드": "00000",
						"도로명시군구코드": "47730",
						"도로명일련번호코드": "01",
						"도로명지상지하코드": "0",
						"도로명코드": "3307052",
						"법정동": "의성읍 중리리",
						"법정동본번코드": "0735",
						"법정동부번코드": "0001",
						"법정동시군구코드": "47730",
						"법정동읍면동코드": "25022",
						"법정동지번코드": "1",
						"아파트": "청구제네스1",
						"월": "12",
						"일": "24",
						"일련번호": "47730-13",
						"전용면적": "84.77",
						"지번": "735-1",
						"지역코드": "47730",
						"층": "3"
					},
					{
						"거래금액": "11,500",
						"건축년도": "1990",
						"년": "2019",
						"도로명": "대동길",
						"도로명건물본번호코드": "00010",
						"도로명건물부번호코드": "00000",
						"도로명시군구코드": "47730",
						"도로명일련번호코드": "01",
						"도로명지상지하코드": "0",
						"도로명코드": "4745092",
						"법정동": "의성읍 상리리",
						"법정동본번코드": "0694",
						"법정동부번코드": "0000",
						"법정동시군구코드": "47730",
						"법정동읍면동코드": "25023",
						"법정동지번코드": "1",
						"아파트": "대동1",
						"월": "12",
						"일": "30",
						"일련번호": "47730-3",
						"전용면적": "84.54",
						"지번": "694",
						"지역코드": "47730",
						"층": "2"
					},
					{
						"거래금액": "4,170",
						"건축년도": "1994",
						"년": "2019",
						"도로명": "치선오상길",
						"도로명건물본번호코드": "00013",
						"도로명건물부번호코드": "00000",
						"도로명시군구코드": "47730",
						"도로명일련번호코드": "01",
						"도로명지상지하코드": "0",
						"도로명코드": "4745497",
						"법정동": "의성읍 도동리",
						"법정동본번코드": "0594",
						"법정동부번코드": "0001",
						"법정동시군구코드": "47730",
						"법정동읍면동코드": "25024",
						"법정동지번코드": "1",
						"아파트": "경신",
						"월": "12",
						"일": "9",
						"일련번호": "47730-8",
						"전용면적": "35.1",
						"지번": "594-1",
						"지역코드": "47730",
						"층": "2"
					}
				]
			},
			"numOfRows": "10",
			"pageNo": "1",
			"totalCount": "3"
		}
	}
}