{
	"response": {
		"header": {
			"resultCode": "00",
			"resultMsg": "NORMAL SERVICE."
		},
		"body": {
			"items": {
				"item": [
					{
						"거래금액": "24,000",
						"건축년도": "2016",
						"년": "2019",
						"도로명": "교육청길",
						"도로명건물본번호코드": "00009",
						"도로명건물부번호코드": "00003",
						"도로명시군구코드": "46820",
						"도로명일련번호코드": "00",
						"도로명지상지하코드": "0",
						"도로명코드": "4682043",
						"법정동": "해남읍 해리",
						"법정동본번코드": "0702",
						"법정동부번코드": "0000",
						"법정동시군구코드": "46820",
						"법정동읍면동코드": "25021",
						"법정동지번코드": "1",
						"아파트": "베네PARK",
						"월": "12",
						"일": "3",
						"일련번호": "46820-89",
						"전용면적": "84.6002",
						"지번": "702",
						"지역코드": "46820",
						"층": "12"
					},
					{
						"거래금액": "2,300",
						"건축년도": "1989",
						"년": "2019",
						"도로명": "해리9길",
						"도로명건물본번호코드": "00014",
						"도로명건물부번호코드": "00000",
						"도로명시군구코드": "46820",
						"도로명일련번호코드": "01",
						"도로명지상지하코드": "0",
						"도로명코드": "4682619",
						"법정동": "해남읍 해리",
						"법정동본번코드": "0572",
						"법정동부번코드": "0000",
						"법정동시군구코드": "46820",
						"법정동읍면동코드": "25021",
						"법정동지번코드": "1",
						"아파트": "미암",
						"월": "12",
						"일": "10",
						"일련번호": "46820-6",
						"전용면적": "52.17",
						"지번": "572",
						"지역코드": "46820",
						"층": "2"
					},
					{
						"거래금액": "15,500",
						"건축년도": "2012",
						"년": "2019",
						"도로명": "해리3길",
						"도로명건물본번호코드": "00006",
						"도로명건물부번호코드": "00000",
						"도로명시군구코드": "46820",
						"도로명일련번호코드": "01",
						"도로명지상지하코드": "0",
						"도로명코드": "4682613",
						"법정동": "해남읍 해리",
						"법정동본번코드": "0690",
						"법정동부번코드": "0000",
						"법정동시군구코드": "46820",
						"법정동읍면동코드": "25021",
						"법정동지번코드": "1",
						"아파트": "성화누리안",
						"월": "12",
						"일": "13",
						"일련번호": "46820-73",
						"전용면적": "73.1145",
						"지번": "690",
						"지역코드": "46820",
						"층": "12"
					},
					{
						"거래금액": "15,150",
						"건축년도": "2012",
						"년": "2019",
						"도로명": "해리3길",
						"도로명건물본번호코드": "00006",
						"도로명건물부번호코드": "00000",
						"도로명시군구코드": "46820",
						"도로명일련번호코드": "01",
						"도로명지상지하코드": "0",
						"도로명코드": "4682613",
						"법정동": "해남읍 해리",
						"법정동본번코드": "0690",
						"법정동부번코드": "0000",
						"법정동시군구코드": "46820",
						"법정동읍면동코드": "25021",
						"법정동지번코드": "1",
						"아파트": "성화누리안",
						"월": "12",
						"일": "20",
						"일련번호": "46820-73",
						"전용면적": "73.5839",
						"지번": "690",
						"지역코드": "46820",
						"층": "8"
					},
					{
						"거래금액": "2,700",
						"건축년도": "1989",
						"년": "2019",
						"도로명": "해리9길",
						"도로명건물본번호코드": "00014",
						"도로명건물부번호코드": "00000",
						"도로명시군구코드": "46820",
						"도로명일련번호코드": "01",
						"도로명지상지하코드": "0",
						"도로명코드": "4682619",
						"법정동": "해남읍 해리",
						"법정동본번코드": "0572",
						"법정동부번코드": "0002",
						"법정동시군구코드": "46820",
						"법정동읍면동코드": "25021",
						"법정동지번코드": "1",
						"아파트": "미암",
						"월": "12",
						"일": "20",
						"일련번호": "46820-6",
						"전용면적": "52.17",
						"지번": "572",
						"지역코드": "46820",
						"층": "2"
					},
					{
						"거래금액": "6,500",
						"건축년도": "1992",
						"년": "2019",
						"도로명": "동초길",
						"도로명건물본번호코드": "00069",
						"도로명건물부번호코드": "00000",
						"도로명시군구코드": "46820",
						"도로명일련번호코드": "01",
						"도로명지상지하코드": "0",
						"도로명코드": "4682139",
						"법정동": "해남읍 해리",
						"법정동본번코드": "0337",
						"법정동부번코드": "0000",
						"법정동시군구코드": "46820",
						"법정동읍면동코드": "25021",
						"법정동지번코드": "1",
						"아파트": "금영",
						"월": "12",
						"일": "24",
						"일련번호": "46820-3",
						"전용면적": "59.82",
						"지번": "305-2",
						"지역코드": "46820",
						"층": "7"
					},
					{
						"거래금액": "5,500",
						"건축년도": "1985",
						"년": "2019",
						"도로명": "북부순환로",
						"도로명건물본번호코드": "00041",
						"도로명건물부번호코드": "00000",
						"도로명시군구코드": "46820",
						"도로명일련번호코드": "01",
						"도로명지상지하코드": "0",
						"도로명코드": "3294009",
						"법정동": "해남읍 해리",
						"법정동본번코드": "0449",
						"법정동부번코드": "0002",
						"법정동시군구코드": "46820",
						"법정동읍면동코드": "25021",
						"법정동지번코드": "1",
						"아파트": "동백",
						"월": "12",
						"일": "26",
						"일련번호": "46820-4",
						"전용면적": "84.21",
						"지번": "449-2",
						"지역코드": "46820",
						"층": "3"
					},
					{
						"거래금액": "12,700",
						"건축년도": "2003",
						"년": "2019",
						"도로명": "해남로",
						"도로명건물본번호코드": "00035",
						"도로명건물부번호코드": "00000",
						"도로명시군구코드": "46820",
						"도로명일련번호코드": "01",
						"도로명지상지하코드": "0",
						"도로명코드": "3294030",
						"법정동": "해남읍 해리",
						"법정동본번코드": "0176",
						"법정동부번코드": "0000",
						"법정동시군구코드": "46820",
						"법정동읍면동코드": "25021",
						"법정동지번코드": "1",
						"아파트": "백두4차",
						"월": "12",
						"일": "26",
						"일련번호": "46820-29",
						"전용면적": "83.3953",
						"지번": "176",
						"지역코드": "46820",
						"층": "13"
					},
					{
						"거래금액": "5,500",
						"건축년도": "1985",
						"년": "2019",
						"도로명": "북부순환로",
						"도로명건물본번호코드": "00041",
						"도로명건물부번호코드": "00000",
						"도로명시군구코드": "46820",
						"도로명일련번호코드": "01",
						"도로명지상지하코드": "0",
						"도로명코드": "3294009",
						"법정동": "해남읍 해리",
						"법정동본번코드": "0449",
						"법정동부번코드": "0002",
						"법정동시군구코드": "46820",
						"법정동읍면동코드": "25021",
						"법정동지번코드": "1",
						"아파트": "동백",
						"월": "12",
						"일": "26",
						"일련번호": "46820-4",
						"전용면적": "84.21",
						"지번": "449-2",
						"지역코드": "46820",
						"층": "3"
					},
					{
						"거래금액": "6,000",
						"건축년도": "1995",
						"년": "2019",
						"도로명": "고도길",
						"도로명건물본번호코드": "00015",
						"도로명건물부번호코드": "00003",
						"도로명시군구코드": "46820",
						"도로명일련번호코드": "01",
						"도로명지상지하코드": "0",
						"도로명코드": "4682028",
						"법정동": "해남읍 고도리",
						"법정동본번코드": "0120",
						"법정동부번코드": "0014",
						"법정동시군구코드": "46820",
						"법정동읍면동코드": "25024",
						"법정동지번코드": "1",
						"아파트": "삼우",
						"월": "12",
						"일": "23",
						"일련번호": "46820-12",
						"전용면적": "59.52",
						"지번": "120-14",
						"지역코드": "46820",
						"층": "8"
					}
				]
			},
			"numOfRows": "10",
			"pageNo": "1",
			"totalCount": "31"
		}
	}
}