{
	"response": {
		"header": {
			"resultCode": "00",
			"resultMsg": "NORMAL SERVICE."
		},
		"body": {
			"items": {
				"item": [
					{
						"거래금액": "19,000",
						"건축년도": "1995",
						"년": "2019",
						"도로명": "북변1로16번길",
						"도로명건물본번호코드": "00034",
						"도로명건물부번호코드": "00000",
						"도로명시군구코드": "41570",
						"도로명일련번호코드": "01",
						"도로명지상지하코드": "0",
						"도로명코드": "4427258",
						"법정동": "북변동",
						"법정동본번코드": "0690",
						"법정동부번코드": "0000",
						"법정동시군구코드": "41570",
						"법정동읍면동코드": "10100",
						"법정동지번코드": "1",
						"아파트": "산호",
						"월": "12",
						"일": "2",
						"일련번호": "41570-2",
						"전용면적": "59.61",
						"지번": "690",
						"지역코드": "41570",
						"층": "4"
					},
					{
						"거래금액": "39,000",
						"건축년도": "1999",
						"년": "2019",
						"도로명": "김포대로926번길",
						"도로명건물본번호코드": "00137",
						"도로명건물부번호코드": "00000",
						"도로명시군구코드": "41570",
						"도로명일련번호코드": "01",
						"도로명지상지하코드": "0",
						"도로명코드": "4427113",
						"법정동": "북변동",
						"법정동본번코드": "0832",
						"법정동부번코드": "0000",
						"법정동시군구코드": "41570",
						"법정동읍면동코드": "10100",
						"법정동지번코드": "1",
						"아파트": "풍년마을(영풍)",
						"월": "12",
						"일": "3",
						"일련번호": "41570-9",
						"전용면적": "134.56",
						"지번": "832",
						"지역코드": "41570",
						"층": "15"
					},
					{
						"거래금액": "19,000",
						"건축년도": "1995",
						"년": "2019",
						"도로명": "북변1로16번길",
						"도로명건물본번호코드": "00034",
						"도로명건물부번호코드": "00000",
						"도로명시군구코드": "41570",
						"도로명일련번호코드": "01",
						"도로명지상지하코드": "0",
						"도로명코드": "4427258",
						"법정동": "북변동",
						"법정동본번코드": "0690",
						"법정동부번코드": "0000",
						"법정동시군구코드": "41570",
						"법정동읍면동코드": "10100",
						"법정동지번코드": "1",
						"아파트": "산호",
						"월": "12",
						"일": "3",
						"일련번호": "41570-2",
						"전용면적": "59.61",
						"지번": "690",
						"지역코드": "41570",
						"층": "11"
					},
					{
						"거래금액": "27,600",
						"건축년도": "1999",
						"년": "2019",
						"도로명": "김포대로926번길",
						"도로명건물본번호코드": "00137",
						"도로명건물부번호코드": "00000",
						"도로명시군구코드": "41570",
						"도로명일련번호코드": "01",
						"도로명지상지하코드": "0",
						"도로명코드": "4427113",
						"법정동": "북변동",
						"법정동본번코드": "0832",
						"법정동부번코드": "0000",
						"법정동시군구코드": "41570",
						"법정동읍면동코드": "10100",
						"법정동지번코드": "1",
						"아파트": "풍년마을(영풍)",
						"월": "12",
						"일": "4",
						"일련번호": "41570-9",
						"전용면적": "134.56",
						"지번": "832",
						"지역코드": "41570",
						"층": "2"
					},
					{
						"거래금액": "24,450",
						"건축년도": "2006",
						"년": "2019",
						"도로명": "봉화로",
						"도로명건물본번호코드": "00090",
						"도로명건물부번호코드": "00003",
						"도로명시군구코드": "41570",
						"도로명일련번호코드": "01",
						"도로명지상지하코드": "0",
						"도로명코드": "3209140",
						"법정동": "북변동",
						"법정동본번코드": "0902",
						"법정동부번코드": "0000",
						"법정동시군구코드": "41570",
						"법정동읍면동코드": "10100",
						"법정동지번코드": "1",
						"아파트": "동변마을(동양파라곤)",
						"월": "12",
						"일": "4",
						"일련번호": "41570-600",
						"전용면적": "84.82",
						"지번": "902",
						"지역코드": "41570",
						"층": "2"
					},
					{
						"거래금액": "33,700",
						"건축년도": "2000",
						"년": "2019",
						"도로명": "김포대로926번길",
						"도로명건물본번호코드": "00046",
						"도로명건물부번호코드": "00000",
						"도로명시군구코드": "41570",
						"도로명일련번호코드": "00",
						"도로명코드": "4427113",
						"법정동": "북변동",
						"법정동본번코드": "0806",
						"법정동부번코드": "0000",
						"법정동시군구코드": "41570",
						"법정동읍면동코드": "10100",
						"법정동지번코드": "1",
						"아파트": "풍년마을(삼성)",
						"월": "12",
						"일": "4",
						"일련번호": "41570-5",
						"전용면적": "149.22",
						"지번": "806",
						"지역코드": "41570",
						"층": "7"
					},
					{
						"거래금액": "35,900",
						"건축년도": "2000",
						"년": "2019",
						"도로명": "김포대로926번길",
						"도로명건물본번호코드": "00046",
						"도로명건물부번호코드": "00000",
						"도로명시군구코드": "41570",
						"도로명일련번호코드": "00",
						"도로명코드": "4427113",
						"법정동": "북변동",
						"법정동본번코드": "0806",
						"법정동부번코드": "0000",
						"법정동시군구코드": "41570",
						"법정동읍면동코드": "10100",
						"법정동지번코드": "1",
						"아파트": "풍년마을(삼성)",
						"월": "12",
						"일": "5",
						"일련번호": "41570-5",
						"전용면적": "149.22",
						"지번": "806",
						"지역코드": "41570",
						"층": "16"
					},
					{
						"거래금액": "18,400",
						"건축년도": "1995",
						"년": "2019",
						"도로명": "북변1로16번길",
						"도로명건물본번호코드": "00034",
						"도로명건물부번호코드": "00000",
						"도로명시군구코드": "41570",
						"도로명일련번호코드": "01",
						"도로명지상지하코드": "0",
						"도로명코드": "4427258",
						"법정동": "북변동",
						"법정동본번코드": "0690",
						"법정동부번코드": "0000",
						"법정동시군구코드": "41570",
						"법정동읍면동코드": "10100",
						"법정동지번코드": "1",
						"아파트": "산호",
						"월": "12",
						"일": "6",
						"일련번호": "41570-2",
						"전용면적": "59.46",
						"지번": "690",
						"지역코드": "41570",
						"층": "8"
					},
					{
						"거래금액": "25,800",
						"건축년도": "2000",
						"년": "2019",
						"도로명": "사우중로73번길",
						"도로명건물본번호코드": "00011",
						"도로명건물부번호코드": "00000",
						"도로명시군구코드": "41570",
						"도로명일련번호코드": "01",
						"도로명지상지하코드": "0",
						"도로명코드": "4427276",
						"법정동": "북변동",
						"법정동본번코드": "0815",
						"법정동부번코드": "0000",
						"법정동시군구코드": "41570",
						"법정동읍면동코드": "10100",
						"법정동지번코드": "1",
						"아파트": "풍년마을(청구)",
						"월": "12",
						"일": "9",
						"일련번호": "41570-10",
						"전용면적": "59.99",
						"지번": "815",
						"지역코드": "41570",
						"층": "3"
					},
					{
						"거래금액": "35,000",
						"건축년도": "1999",
						"년": "2019",
						"도로명": "김포대로926번길",
						"도로명건물본번호코드": "00088",
						"도로명건물부번호코드": "00027",
						"도로명시군구코드": "41570",
						"도로명일련번호코드": "00",
						"도로명코드": "4427113",
						"법정동": "북변동",
						"법정동본번코드": "0812",
						"법정동부번코드": "0000",
						"법정동시군구코드": "41570",
						"법정동읍면동코드": "10100",
						"법정동지번코드": "1",
						"아파트": "풍년마을(신일)",
						"월": "12",
						"일": "13",
						"일련번호": "41570-8",
						"전용면적": "126.015",
						"지번": "812",
						"지역코드": "41570",
						"층": "10"
					}
				]
			},
			"numOfRows": "10",
			"pageNo": "1",
			"totalCount": "329"
		}
	}
}