{
	"response": {
		"header": {
			"resultCode": "00",
			"resultMsg": "NORMAL SERVICE."
		},
		"body": {
			"items": {
				"item": [
					{
						"거래금액": "90,000",
						"건축년도": "2002",
						"년": "2019",
						"도로명": "도신로29길",
						"도로명건물본번호코드": "00028",
						"도로명건물부번호코드": "00000",
						"도로명시군구코드": "11560",
						"도로명일련번호코드": "01",
						"도로명지상지하코드": "0",
						"도로명코드": "4154317",
						"법정동": "영등포동",
						"법정동본번코드": "0647",
						"법정동부번코드": "0001",
						"법정동시군구코드": "11560",
						"법정동읍면동코드": "10100",
						"법정동지번코드": "1",
						"아파트": "영등포푸르지오",
						"월": "12",
						"일": "5",
						"일련번호": "11560-2",
						"전용면적": "84.908",
						"지번": "647",
						"지역코드": "11560",
						"층": "16"
					},
					{
						"거래금액": "85,000",
						"건축년도": "2002",
						"년": "2019",
						"도로명": "도신로29길",
						"도로명건물본번호코드": "00028",
						"도로명건물부번호코드": "00000",
						"도로명시군구코드": "11560",
						"도로명일련번호코드": "01",
						"도로명지상지하코드": "0",
						"도로명코드": "4154317",
						"법정동": "영등포동",
						"법정동본번코드": "0647",
						"법정동부번코드": "0000",
						"법정동시군구코드": "11560",
						"법정동읍면동코드": "10100",
						"법정동지번코드": "1",
						"아파트": "영등포푸르지오",
						"월": "12",
						"일": "7",
						"일련번호": "11560-2",
						"전용면적": "73.133",
						"지번": "647",
						"지역코드": "11560",
						"층": "16"
					},
					{
						"거래금액": "80,000",
						"건축년도": "2002",
						"년": "2019",
						"도로명": "도신로29길",
						"도로명건물본번호코드": "00028",
						"도로명건물부번호코드": "00000",
						"도로명시군구코드": "11560",
						"도로명일련번호코드": "01",
						"도로명지상지하코드": "0",
						"도로명코드": "4154317",
						"법정동": "영등포동",
						"법정동본번코드": "0647",
						"법정동부번코드": "0000",
						"법정동시군구코드": "11560",
						"법정동읍면동코드": "10100",
						"법정동지번코드": "1",
						"아파트": "영등포푸르지오",
						"월": "12",
						"일": "9",
						"일련번호": "11560-2",
						"전용면적": "59.912",
						"지번": "647",
						"지역코드": "11560",
						"층": "18"
					},
					{
						"거래금액": "77,000",
						"건축년도": "2002",
						"년": "2019",
						"도로명": "도신로29길",
						"도로명건물본번호코드": "00028",
						"도로명건물부번호코드": "00000",
						"도로명시군구코드": "11560",
						"도로명일련번호코드": "01",
						"도로명지상지하코드": "0",
						"도로명코드": "4154317",
						"법정동": "영등포동",
						"법정동본번코드": "0647",
						"법정동부번코드": "0000",
						"법정동시군구코드": "11560",
						"법정동읍면동코드": "10100",
						"법정동지번코드": "1",
						"아파트": "영등포푸르지오",
						"월": "12",
						"일": "9",
						"일련번호": "11560-2",
						"전용면적": "59.912",
						"지번": "647",
						"지역코드": "11560",
						"층": "15"
					},
					{
						"거래금액": "80,000",
						"건축년도": "2002",
						"년": "2019",
						"도로명": "도신로29길",
						"도로명건물본번호코드": "00028",
						"도로명건물부번호코드": "00000",
						"도로명시군구코드": "11560",
						"도로명일련번호코드": "01",
						"도로명지상지하코드": "0",
						"도로명코드": "4154317",
						"법정동": "영등포동",
						"법정동본번코드": "0647",
						"법정동부번코드": "0000",
						"법정동시군구코드": "11560",
						"법정동읍면동코드": "10100",
						"법정동지번코드": "1",
						"아파트": "영등포푸르지오",
						"월": "12",
						"일": "9",
						"일련번호": "11560-2",
						"전용면적": "73.133",
						"지번": "647",
						"지역코드": "11560",
						"층": "20"
					},
					{
						"거래금액": "87,500",
						"건축년도": "2002",
						"년": "2019",
						"도로명": "도신로29길",
						"도로명건물본번호코드": "00028",
						"도로명건물부번호코드": "00000",
						"도로명시군구코드": "11560",
						"도로명일련번호코드": "01",
						"도로명지상지하코드": "0",
						"도로명코드": "4154317",
						"법정동": "영등포동",
						"법정동본번코드": "0647",
						"법정동부번코드": "0000",
						"법정동시군구코드": "11560",
						"법정동읍면동코드": "10100",
						"법정동지번코드": "1",
						"아파트": "영등포푸르지오",
						"월": "12",
						"일": "13",
						"일련번호": "11560-2",
						"전용면적": "84.908",
						"지번": "647",
						"지역코드": "11560",
						"층": "19"
					},
					{
						"거래금액": "88,000",
						"건축년도": "2002",
						"년": "2019",
						"도로명": "도신로29길",
						"도로명건물본번호코드": "00028",
						"도로명건물부번호코드": "00000",
						"도로명시군구코드": "11560",
						"도로명일련번호코드": "01",
						"도로명지상지하코드": "0",
						"도로명코드": "4154317",
						"법정동": "영등포동",
						"법정동본번코드": "0647",
						"법정동부번코드": "0000",
						"법정동시군구코드": "11560",
						"법정동읍면동코드": "10100",
						"법정동지번코드": "1",
						"아파트": "영등포푸르지오",
						"월": "12",
						"일": "14",
						"일련번호": "11560-2",
						"전용면적": "79.777",
						"지번": "647",
						"지역코드": "11560",
						"층": "10"
					},
					{
						"거래금액": "89,500",
						"건축년도": "2002",
						"년": "2019",
						"도로명": "도신로29길",
						"도로명건물본번호코드": "00028",
						"도로명건물부번호코드": "00000",
						"도로명시군구코드": "11560",
						"도로명일련번호코드": "01",
						"도로명지상지하코드": "0",
						"도로명코드": "4154317",
						"법정동": "영등포동",
						"법정동본번코드": "0647",
						"법정동부번코드": "0000",
						"법정동시군구코드": "11560",
						"법정동읍면동코드": "10100",
						"법정동지번코드": "1",
						"아파트": "영등포푸르지오",
						"월": "12",
						"일": "16",
						"일련번호": "11560-2",
						"전용면적": "79.777",
						"지번": "647",
						"지역코드": "11560",
						"층": "18"
					},
					{
						"거래금액": "87,700",
						"건축년도": "2002",
						"년": "2019",
						"도로명": "도신로29길",
						"도로명건물본번호코드": "00028",
						"도로명건물부번호코드": "00000",
						"도로명시군구코드": "11560",
						"도로명일련번호코드": "01",
						"도로명지상지하코드": "0",
						"도로명코드": "4154317",
						"법정동": "영등포동",
						"법정동본번코드": "0647",
						"법정동부번코드": "0000",
						"법정동시군구코드": "11560",
						"법정동읍면동코드": "10100",
						"법정동지번코드": "1",
						"아파트": "영등포푸르지오",
						"월": "12",
						"일": "25",
						"일련번호": "11560-2",
						"전용면적": "73.133",
						"지번": "647",
						"지역코드": "11560",
						"층": "18"
					},
					{
						"거래금액": "90,000",
						"건축년도": "2002",
						"년": "2019",
						"도로명": "도신로29길",
						"도로명건물본번호코드": "00028",
						"도로명건물부번호코드": "00000",
						"도로명시군구코드": "11560",
						"도로명일련번호코드": "01",
						"도로명지상지하코드": "0",
						"도로명코드": "4154317",
						"법정동": "영등포동",
						"법정동본번코드": "0647",
						"법정동부번코드": "0000",
						"법정동시군구코드": "11560",
						"법정동읍면동코드": "10100",
						"법정동지번코드": "1",
						"아파트": "영등포푸르지오",
						"월": "12",
						"일": "27",
						"일련번호": "11560-2",
						"전용면적": "79.777",
						"지번": "647",
						"지역코드": "11560",
						"층": "3"
					}
				]
			},
			"numOfRows": "10",
			"pageNo": "1",
			"totalCount": "151"
		}
	}
}